{
  "/js/app.js": "/js/app.7705dd25e1fc2df155b0.js",
  "/css/web.css": "/css/web.7705dd25e1fc2df155b0.css",
  "/css/app.css": "/css/app.bcad1439cb71e3c47072c18b21fcf707.css",
  "/js/app.js.map": "/js/app.7705dd25e1fc2df155b0.js.map",
  "/css/web.css.map": "/css/web.7705dd25e1fc2df155b0.css.map",
  "/css/app.css.map": "/css/app.bcad1439cb71e3c47072c18b21fcf707.css.map",
  "vendor.js": "vendor.7705dd25e1fc2df155b0.js",
  "vendor.js.map": "vendor.7705dd25e1fc2df155b0.js.map",
  "manifest.js": "manifest.7705dd25e1fc2df155b0.js",
  "manifest.js.map": "manifest.7705dd25e1fc2df155b0.js.map"
}